aliyunsdkschedulerx2/__init__.py
aliyunsdkschedulerx2/endpoint.py
aliyunsdkschedulerx2/request/__init__.py
aliyunsdkschedulerx2/request/v20190430/BatchDeleteJobsRequest.py
aliyunsdkschedulerx2/request/v20190430/BatchDeleteRouteStrategyRequest.py
aliyunsdkschedulerx2/request/v20190430/BatchDisableJobsRequest.py
aliyunsdkschedulerx2/request/v20190430/BatchEnableJobsRequest.py
aliyunsdkschedulerx2/request/v20190430/CreateAppGroupRequest.py
aliyunsdkschedulerx2/request/v20190430/CreateJobRequest.py
aliyunsdkschedulerx2/request/v20190430/CreateNamespaceRequest.py
aliyunsdkschedulerx2/request/v20190430/CreateRouteStrategyRequest.py
aliyunsdkschedulerx2/request/v20190430/CreateWorkflowRequest.py
aliyunsdkschedulerx2/request/v20190430/DeleteAppGroupRequest.py
aliyunsdkschedulerx2/request/v20190430/DeleteJobRequest.py
aliyunsdkschedulerx2/request/v20190430/DeleteNamespaceRequest.py
aliyunsdkschedulerx2/request/v20190430/DeleteRouteStrategyRequest.py
aliyunsdkschedulerx2/request/v20190430/DeleteWorkflowRequest.py
aliyunsdkschedulerx2/request/v20190430/DescribeRegionsRequest.py
aliyunsdkschedulerx2/request/v20190430/DesignateWorkersRequest.py
aliyunsdkschedulerx2/request/v20190430/DisableJobRequest.py
aliyunsdkschedulerx2/request/v20190430/DisableWorkflowRequest.py
aliyunsdkschedulerx2/request/v20190430/EnableJobRequest.py
aliyunsdkschedulerx2/request/v20190430/EnableWorkflowRequest.py
aliyunsdkschedulerx2/request/v20190430/ExecuteJobRequest.py
aliyunsdkschedulerx2/request/v20190430/ExecuteWorkflowRequest.py
aliyunsdkschedulerx2/request/v20190430/GetAppGroupRequest.py
aliyunsdkschedulerx2/request/v20190430/GetJobInfoRequest.py
aliyunsdkschedulerx2/request/v20190430/GetJobInstanceListRequest.py
aliyunsdkschedulerx2/request/v20190430/GetJobInstanceRequest.py
aliyunsdkschedulerx2/request/v20190430/GetLogRequest.py
aliyunsdkschedulerx2/request/v20190430/GetOverviewRequest.py
aliyunsdkschedulerx2/request/v20190430/GetWorkFlowRequest.py
aliyun_python_sdk_schedulerx2-1.1.15.dist-info/LICENSE
aliyun_python_sdk_schedulerx2-1.1.15.dist-info/METADATA
aliyun_python_sdk_schedulerx2-1.1.15.dist-info/WHEEL
aliyun_python_sdk_schedulerx2-1.1.15.dist-info/top_level.txt
aliyun_python_sdk_schedulerx2-1.1.15.dist-info/RECORD
